complete_shuffle_package/__init__.py
complete_shuffle_package/complete_shuffle_module.py
complete_shuffle-1.1.2.dist-info/LICENSE
complete_shuffle-1.1.2.dist-info/METADATA
complete_shuffle-1.1.2.dist-info/WHEEL
complete_shuffle-1.1.2.dist-info/top_level.txt
complete_shuffle-1.1.2.dist-info/RECORD
