Metadata-Version: 2.1
Name: complete-shuffle
Version: 1.1.2
Summary: Complete shuffling of lists with true random or pseudo random sequences.
Home-page: https://github.com/fsssosei/complete_shuffle
Author: sosei
Author-email: fss.sosei@gmail.com
License: GNU Affero General Public License v3
Keywords: complete,shuffle,cyclic permutation,derangement,random
Platform: UNKNOWN
Classifier: Development Status :: 5 - Production/Stable
Classifier: License :: OSI Approved :: GNU Affero General Public License v3
Classifier: Programming Language :: Python :: 3.8
Requires-Python: >=3.8
Requires-Dist: gmpy2 (>=2.0.8)
Requires-Dist: pure-nrng (>=1.1.0)
Requires-Dist: pure-prng (>=2.9.0)
